[
    {
        "id": 1,
        "ingles": "Red",
        "portugues": "Vermelho",
        "fraseIngles": "The red rose smells beautiful.",
        "frasePortugues": "A rosa vermelha cheira lindamente.",
        "subtopico": "Cores",
        "topico": "Outros assuntos"
    },
    {
        "id": 2,
        "ingles": "Blue",
        "portugues": "Azul",
        "fraseIngles": "The sky is bright blue today.",
        "frasePortugues": "O céu está azul vivo hoje.",
        "subtopico": "Cores",
        "topico": "Outros assuntos"
    },
    {
        "id": 3,
        "ingles": "Green",
        "portugues": "Verde",
        "fraseIngles": "Fresh grass is bright green.",
        "frasePortugues": "Grama fresca é verde vivo.",
        "subtopico": "Cores",
        "topico": "Outros assuntos"
    },
    {
        "id": 4,
        "ingles": "Yellow",
        "portugues": "Amarelo",
        "fraseIngles": "The sun looks yellow in the sky.",
        "frasePortugues": "O sol parece amarelo no céu.",
        "subtopico": "Cores",
        "topico": "Outros assuntos"
    },
    {
        "id": 5,
        "ingles": "Orange",
        "portugues": "Laranja",
        "fraseIngles": "The pumpkin is bright orange.",
        "frasePortugues": "A abóbora é laranja vivo.",
        "subtopico": "Cores",
        "topico": "Outros assuntos"
    },
    {
        "id": 6,
        "ingles": "Purple",
        "portugues": "Roxo",
        "fraseIngles": "Grapes can be purple or green.",
        "frasePortugues": "Uvas podem ser roxas ou verdes.",
        "subtopico": "Cores",
        "topico": "Outros assuntos"
    },
    {
        "id": 7,
        "ingles": "Pink",
        "portugues": "Rosa",
        "fraseIngles": "Cherry blossoms are soft pink.",
        "frasePortugues": "Flores de cerejeira são rosa suave.",
        "subtopico": "Cores",
        "topico": "Outros assuntos"
    },
    {
        "id": 8,
        "ingles": "Brown",
        "portugues": "Marrom",
        "fraseIngles": "Tree bark is usually brown.",
        "frasePortugues": "Casca de árvore geralmente é marrom.",
        "subtopico": "Cores",
        "topico": "Outros assuntos"
    },
    {
        "id": 9,
        "ingles": "Black",
        "portugues": "Preto",
        "fraseIngles": "The cat has shiny black fur.",
        "frasePortugues": "O gato tem pelo preto brilhante.",
        "subtopico": "Cores",
        "topico": "Outros assuntos"
    },
    {
        "id": 10,
        "ingles": "White",
        "portugues": "Branco",
        "fraseIngles": "Fresh snow is pure white.",
        "frasePortugues": "Neve fresca é branca pura.",
        "subtopico": "Cores",
        "topico": "Outros assuntos"
    },
    {
        "id": 11,
        "ingles": "Gray",
        "portugues": "Cinza",
        "fraseIngles": "Storm clouds are dark gray.",
        "frasePortugues": "Nuvens de tempestade são cinza escuro.",
        "subtopico": "Cores",
        "topico": "Outros assuntos"
    },
    {
        "id": 12,
        "ingles": "Grey",
        "portugues": "Cinza (grafia britânica)",
        "fraseIngles": "British spelling uses grey with an 'e'.",
        "frasePortugues": "Grafia britânica usa grey com 'e'.",
        "subtopico": "Cores",
        "topico": "Outros assuntos"
    },
    {
        "id": 13,
        "ingles": "Crimson",
        "portugues": "Carmesim",
        "fraseIngles": "The flag has a crimson stripe.",
        "frasePortugues": "A bandeira tem uma faixa carmesim.",
        "subtopico": "Cores",
        "topico": "Outros assuntos"
    },
    {
        "id": 14,
        "ingles": "Scarlet",
        "portugues": "Escarlate",
        "fraseIngles": "The bird has scarlet feathers.",
        "frasePortugues": "O pássaro tem penas escarlates.",
        "subtopico": "Cores",
        "topico": "Outros assuntos"
    },
    {
        "id": 15,
        "ingles": "Maroon",
        "portugues": "Bordô",
        "fraseIngles": "The wine is deep maroon color.",
        "frasePortugues": "O vinho é cor bordô profunda.",
        "subtopico": "Cores",
        "topico": "Outros assuntos"
    },
    {
        "id": 16,
        "ingles": "Burgundy",
        "portugues": "Borgonha",
        "fraseIngles": "Her dress is elegant burgundy.",
        "frasePortugues": "Seu vestido é borgonha elegante.",
        "subtopico": "Cores",
        "topico": "Outros assuntos"
    },
    {
        "id": 17,
        "ingles": "Cherry red",
        "portugues": "Vermelho cereja",
        "fraseIngles": "The lipstick is cherry red.",
        "frasePortugues": "O batom é vermelho cereja.",
        "subtopico": "Cores",
        "topico": "Outros assuntos"
    },
    {
        "id": 18,
        "ingles": "Fire red",
        "portugues": "Vermelho fogo",
        "fraseIngles": "The sports car is fire red.",
        "frasePortugues": "O carro esportivo é vermelho fogo.",
        "subtopico": "Cores",
        "topico": "Outros assuntos"
    },
    {
        "id": 19,
        "ingles": "Blood red",
        "portugues": "Vermelho sangue",
        "fraseIngles": "The sunset sky was blood red.",
        "frasePortugues": "O céu do pôr do sol estava vermelho sangue.",
        "subtopico": "Cores",
        "topico": "Outros assuntos"
    },
    {
        "id": 20,
        "ingles": "Rose red",
        "portugues": "Vermelho rosa",
        "fraseIngles": "The valentine card is rose red.",
        "frasePortugues": "O cartão de dia dos namorados é vermelho rosa.",
        "subtopico": "Cores",
        "topico": "Outros assuntos"
    },
    {
        "id": 21,
        "ingles": "Brick red",
        "portugues": "Vermelho tijolo",
        "fraseIngles": "The old building is brick red.",
        "frasePortugues": "O prédio antigo é vermelho tijolo.",
        "subtopico": "Cores",
        "topico": "Outros assuntos"
    },
    {
        "id": 22,
        "ingles": "Ruby red",
        "portugues": "Vermelho rubi",
        "fraseIngles": "The gemstone is ruby red.",
        "frasePortugues": "A pedra preciosa é vermelho rubi.",
        "subtopico": "Cores",
        "topico": "Outros assuntos"
    },
    {
        "id": 23,
        "ingles": "Navy blue",
        "portugues": "Azul marinho",
        "fraseIngles": "His uniform is navy blue.",
        "frasePortugues": "Seu uniforme é azul marinho.",
        "subtopico": "Cores",
        "topico": "Outros assuntos"
    },
    {
        "id": 24,
        "ingles": "Sky blue",
        "portugues": "Azul céu",
        "fraseIngles": "The baby's room is sky blue.",
        "frasePortugues": "O quarto do bebê é azul céu.",
        "subtopico": "Cores",
        "topico": "Outros assuntos"
    },
    {
        "id": 25,
        "ingles": "Royal blue",
        "portugues": "Azul real",
        "fraseIngles": "The flag has royal blue sections.",
        "frasePortugues": "A bandeira tem seções azul real.",
        "subtopico": "Cores",
        "topico": "Outros assuntos"
    },
    {
        "id": 26,
        "ingles": "Electric blue",
        "portugues": "Azul elétrico",
        "fraseIngles": "The neon sign glows electric blue.",
        "frasePortugues": "O letreiro neon brilha azul elétrico.",
        "subtopico": "Cores",
        "topico": "Outros assuntos"
    },
    {
        "id": 27,
        "ingles": "Powder blue",
        "portugues": "Azul bebê",
        "fraseIngles": "The nursery walls are powder blue.",
        "frasePortugues": "As paredes do berçário são azul bebê.",
        "subtopico": "Cores",
        "topico": "Outros assuntos"
    },
    {
        "id": 28,
        "ingles": "Turquoise",
        "portugues": "Turquesa",
        "fraseIngles": "The tropical water is turquoise.",
        "frasePortugues": "A água tropical é turquesa.",
        "subtopico": "Cores",
        "topico": "Outros assuntos"
    },
    {
        "id": 29,
        "ingles": "Teal",
        "portugues": "Verde-azulado",
        "fraseIngles": "The peacock's feathers are teal.",
        "frasePortugues": "As penas do pavão são verde-azuladas.",
        "subtopico": "Cores",
        "topico": "Outros assuntos"
    },
    {
        "id": 30,
        "ingles": "Aqua",
        "portugues": "Água-marinha",
        "fraseIngles": "The swimming pool is aqua blue.",
        "frasePortugues": "A piscina é azul água-marinha.",
        "subtopico": "Cores",
        "topico": "Outros assuntos"
    },
    {
        "id": 31,
        "ingles": "Cyan",
        "portugues": "Ciano",
        "fraseIngles": "The printer uses cyan ink.",
        "frasePortugues": "A impressora usa tinta ciano.",
        "subtopico": "Cores",
        "topico": "Outros assuntos"
    },
    {
        "id": 32,
        "ingles": "Cobalt blue",
        "portugues": "Azul cobalto",
        "fraseIngles": "The artist mixed cobalt blue paint.",
        "frasePortugues": "O artista misturou tinta azul cobalto.",
        "subtopico": "Cores",
        "topico": "Outros assuntos"
    },
    {
        "id": 33,
        "ingles": "Indigo",
        "portugues": "Índigo",
        "fraseIngles": "Indigo is between blue and purple.",
        "frasePortugues": "Índigo fica entre azul e roxo.",
        "subtopico": "Cores",
        "topico": "Outros assuntos"
    },
    {
        "id": 34,
        "ingles": "Forest green",
        "portugues": "Verde floresta",
        "fraseIngles": "The pine trees are forest green.",
        "frasePortugues": "Os pinheiros são verde floresta.",
        "subtopico": "Cores",
        "topico": "Outros assuntos"
    },
    {
        "id": 35,
        "ingles": "Lime green",
        "portugues": "Verde limão",
        "fraseIngles": "The highlighter is lime green.",
        "frasePortugues": "O marca-texto é verde limão.",
        "subtopico": "Cores",
        "topico": "Outros assuntos"
    },
    {
        "id": 36,
        "ingles": "Emerald green",
        "portugues": "Verde esmeralda",
        "fraseIngles": "Her ring has an emerald green stone.",
        "frasePortugues": "Seu anel tem uma pedra verde esmeralda.",
        "subtopico": "Cores",
        "topico": "Outros assuntos"
    },
    {
        "id": 37,
        "ingles": "Mint green",
        "portugues": "Verde menta",
        "fraseIngles": "The bathroom tiles are mint green.",
        "frasePortugues": "Os azulejos do banheiro são verde menta.",
        "subtopico": "Cores",
        "topico": "Outros assuntos"
    },
    {
        "id": 38,
        "ingles": "Olive green",
        "portugues": "Verde oliva",
        "fraseIngles": "Military uniforms are olive green.",
        "frasePortugues": "Uniformes militares são verde oliva.",
        "subtopico": "Cores",
        "topico": "Outros assuntos"
    },
    {
        "id": 39,
        "ingles": "Sage green",
        "portugues": "Verde sálvia",
        "fraseIngles": "The kitchen cabinets are sage green.",
        "frasePortugues": "Os armários da cozinha são verde sálvia.",
        "subtopico": "Cores",
        "topico": "Outros assuntos"
    },
    {
        "id": 40,
        "ingles": "Sea green",
        "portugues": "Verde mar",
        "fraseIngles": "The ocean looks sea green today.",
        "frasePortugues": "O oceano parece verde mar hoje.",
        "subtopico": "Cores",
        "topico": "Outros assuntos"
    },
    {
        "id": 41,
        "ingles": "Kelly green",
        "portugues": "Verde irlandês",
        "fraseIngles": "The shamrock is kelly green.",
        "frasePortugues": "O trevo é verde irlandês.",
        "subtopico": "Cores",
        "topico": "Outros assuntos"
    },
    {
        "id": 42,
        "ingles": "Jade green",
        "portugues": "Verde jade",
        "fraseIngles": "The bracelet is jade green.",
        "frasePortugues": "A pulseira é verde jade.",
        "subtopico": "Cores",
        "topico": "Outros assuntos"
    },
    {
        "id": 43,
        "ingles": "Neon green",
        "portugues": "Verde neon",
        "fraseIngles": "The safety vest is neon green.",
        "frasePortugues": "O colete de segurança é verde neon.",
        "subtopico": "Cores",
        "topico": "Outros assuntos"
    },
    {
        "id": 44,
        "ingles": "Golden yellow",
        "portugues": "Amarelo dourado",
        "fraseIngles": "The wheat field is golden yellow.",
        "frasePortugues": "O campo de trigo é amarelo dourado.",
        "subtopico": "Cores",
        "topico": "Outros assuntos"
    },
    {
        "id": 45,
        "ingles": "Lemon yellow",
        "portugues": "Amarelo limão",
        "fraseIngles": "The kitchen walls are lemon yellow.",
        "frasePortugues": "As paredes da cozinha são amarelo limão.",
        "subtopico": "Cores",
        "topico": "Outros assuntos"
    },
    {
        "id": 46,
        "ingles": "Canary yellow",
        "portugues": "Amarelo canário",
        "fraseIngles": "The bird is bright canary yellow.",
        "frasePortugues": "O pássaro é amarelo canário vivo.",
        "subtopico": "Cores",
        "topico": "Outros assuntos"
    },
    {
        "id": 47,
        "ingles": "Sunshine yellow",
        "portugues": "Amarelo sol",
        "fraseIngles": "The daffodils are sunshine yellow.",
        "frasePortugues": "Os narcisos são amarelo sol.",
        "subtopico": "Cores",
        "topico": "Outros assuntos"
    },
    {
        "id": 48,
        "ingles": "Butter yellow",
        "portugues": "Amarelo manteiga",
        "fraseIngles": "The baby's blanket is butter yellow.",
        "frasePortugues": "A manta do bebê é amarelo manteiga.",
        "subtopico": "Cores",
        "topico": "Outros assuntos"
    },
    {
        "id": 49,
        "ingles": "Amber yellow",
        "portugues": "Amarelo âmbar",
        "fraseIngles": "The honey is amber yellow.",
        "frasePortugues": "O mel é amarelo âmbar.",
        "subtopico": "Cores",
        "topico": "Outros assuntos"
    },
    {
        "id": 50,
        "ingles": "Mustard yellow",
        "portugues": "Amarelo mostarda",
        "fraseIngles": "The vintage car is mustard yellow.",
        "frasePortugues": "O carro vintage é amarelo mostarda.",
        "subtopico": "Cores",
        "topico": "Outros assuntos"
    },
    {
        "id": 51,
        "ingles": "Cream",
        "portugues": "Creme",
        "fraseIngles": "The wedding dress is cream colored.",
        "frasePortugues": "O vestido de noiva é cor de creme.",
        "subtopico": "Cores",
        "topico": "Outros assuntos"
    },
    {
        "id": 52,
        "ingles": "Ivory",
        "portugues": "Marfim",
        "fraseIngles": "The piano keys are ivory white.",
        "frasePortugues": "As teclas do piano são branco marfim.",
        "subtopico": "Cores",
        "topico": "Outros assuntos"
    },
    {
        "id": 53,
        "ingles": "Peach",
        "portugues": "Pêssego",
        "fraseIngles": "The nursery is painted soft peach.",
        "frasePortugues": "O berçário é pintado de pêssego suave.",
        "subtopico": "Cores",
        "topico": "Outros assuntos"
    },
    {
        "id": 54,
        "ingles": "Coral",
        "portugues": "Coral",
        "fraseIngles": "The tropical fish is bright coral.",
        "frasePortugues": "O peixe tropical é coral vivo.",
        "subtopico": "Cores",
        "topico": "Outros assuntos"
    },
    {
        "id": 55,
        "ingles": "Tangerine",
        "portugues": "Tangerina",
        "fraseIngles": "The sunset is tangerine orange.",
        "frasePortugues": "O pôr do sol é laranja tangerina.",
        "subtopico": "Cores",
        "topico": "Outros assuntos"
    },
    {
        "id": 56,
        "ingles": "Rust",
        "portugues": "Ferrugem",
        "fraseIngles": "The old gate is rust colored.",
        "frasePortugues": "O portão velho é cor de ferrugem.",
        "subtopico": "Cores",
        "topico": "Outros assuntos"
    },
    {
        "id": 57,
        "ingles": "Copper",
        "portugues": "Cobre",
        "fraseIngles": "The pot has a copper finish.",
        "frasePortugues": "A panela tem acabamento cobre.",
        "subtopico": "Cores",
        "topico": "Outros assuntos"
    },
    {
        "id": 58,
        "ingles": "Bronze",
        "portugues": "Bronze",
        "fraseIngles": "The statue is bronze colored.",
        "frasePortugues": "A estátua é cor de bronze.",
        "subtopico": "Cores",
        "topico": "Outros assuntos"
    },
    {
        "id": 59,
        "ingles": "Lavender",
        "portugues": "Lavanda",
        "fraseIngles": "The flowers are soft lavender.",
        "frasePortugues": "As flores são lavanda suave.",
        "subtopico": "Cores",
        "topico": "Outros assuntos"
    },
    {
        "id": 60,
        "ingles": "Violet",
        "portugues": "Violeta",
        "fraseIngles": "The evening sky turns violet.",
        "frasePortugues": "O céu da tarde fica violeta.",
        "subtopico": "Cores",
        "topico": "Outros assuntos"
    },
    {
        "id": 61,
        "ingles": "Plum",
        "portugues": "Ameixa",
        "fraseIngles": "Her lipstick is dark plum.",
        "frasePortugues": "Seu batom é ameixa escuro.",
        "subtopico": "Cores",
        "topico": "Outros assuntos"
    },
    {
        "id": 62,
        "ingles": "Grape",
        "portugues": "Uva",
        "fraseIngles": "The curtains are grape purple.",
        "frasePortugues": "As cortinas são roxo uva.",
        "subtopico": "Cores",
        "topico": "Outros assuntos"
    },
    {
        "id": 63,
        "ingles": "Magenta",
        "portugues": "Magenta",
        "fraseIngles": "The printer uses magenta ink.",
        "frasePortugues": "A impressora usa tinta magenta.",
        "subtopico": "Cores",
        "topico": "Outros assuntos"
    },
    {
        "id": 64,
        "ingles": "Fuchsia",
        "portugues": "Fúcsia",
        "fraseIngles": "The tropical flower is bright fuchsia.",
        "frasePortugues": "A flor tropical é fúcsia vivo.",
        "subtopico": "Cores",
        "topico": "Outros assuntos"
    },
    {
        "id": 65,
        "ingles": "Lilac",
        "portugues": "Lilás",
        "fraseIngles": "The spring flowers are pale lilac.",
        "frasePortugues": "As flores da primavera são lilás pálido.",
        "subtopico": "Cores",
        "topico": "Outros assuntos"
    },
    {
        "id": 66,
        "ingles": "Orchid",
        "portugues": "Orquídea",
        "fraseIngles": "The elegant flower is orchid purple.",
        "frasePortugues": "A flor elegante é roxo orquídea.",
        "subtopico": "Cores",
        "topico": "Outros assuntos"
    },
    {
        "id": 67,
        "ingles": "Mauve",
        "portugues": "Malva",
        "fraseIngles": "The vintage wallpaper is mauve.",
        "frasePortugues": "O papel de parede vintage é malva.",
        "subtopico": "Cores",
        "topico": "Outros assuntos"
    },
    {
        "id": 68,
        "ingles": "Periwinkle",
        "portugues": "Pervinca",
        "fraseIngles": "The small flowers are periwinkle blue.",
        "frasePortugues": "As pequenas flores são azul pervinca.",
        "subtopico": "Cores",
        "topico": "Outros assuntos"
    },
    {
        "id": 69,
        "ingles": "Hot pink",
        "portugues": "Rosa choque",
        "fraseIngles": "The neon sign is hot pink.",
        "frasePortugues": "O letreiro neon é rosa choque.",
        "subtopico": "Cores",
        "topico": "Outros assuntos"
    },
    {
        "id": 70,
        "ingles": "Bubblegum pink",
        "portugues": "Rosa chiclete",
        "fraseIngles": "The little girl's dress is bubblegum pink.",
        "frasePortugues": "O vestido da garotinha é rosa chiclete.",
        "subtopico": "Cores",
        "topico": "Outros assuntos"
    },
    {
        "id": 71,
        "ingles": "Baby pink",
        "portugues": "Rosa bebê",
        "fraseIngles": "The nursery is decorated in baby pink.",
        "frasePortugues": "O berçário é decorado em rosa bebê.",
        "subtopico": "Cores",
        "topico": "Outros assuntos"
    },
    {
        "id": 72,
        "ingles": "Rose pink",
        "portugues": "Rosa",
        "fraseIngles": "The valentine flowers are rose pink.",
        "frasePortugues": "As flores do dia dos namorados são rosa.",
        "subtopico": "Cores",
        "topico": "Outros assuntos"
    },
    {
        "id": 73,
        "ingles": "Salmon pink",
        "portugues": "Rosa salmão",
        "fraseIngles": "The sunset clouds are salmon pink.",
        "frasePortugues": "As nuvens do pôr do sol são rosa salmão.",
        "subtopico": "Cores",
        "topico": "Outros assuntos"
    },
    {
        "id": 74,
        "ingles": "Dusty rose",
        "portugues": "Rosa empoeirado",
        "fraseIngles": "The vintage chair is dusty rose.",
        "frasePortugues": "A cadeira vintage é rosa empoeirado.",
        "subtopico": "Cores",
        "topico": "Outros assuntos"
    },
    {
        "id": 75,
        "ingles": "Chocolate brown",
        "portugues": "Marrom chocolate",
        "fraseIngles": "The leather sofa is chocolate brown.",
        "frasePortugues": "O sofá de couro é marrom chocolate.",
        "subtopico": "Cores",
        "topico": "Outros assuntos"
    },
    {
        "id": 76,
        "ingles": "Coffee brown",
        "portugues": "Marrom café",
        "fraseIngles": "His eyes are warm coffee brown.",
        "frasePortugues": "Seus olhos são marrom café caloroso.",
        "subtopico": "Cores",
        "topico": "Outros assuntos"
    },
    {
        "id": 77,
        "ingles": "Chestnut brown",
        "portugues": "Marrom castanha",
        "fraseIngles": "Her hair is rich chestnut brown.",
        "frasePortugues": "Seu cabelo é marrom castanha rico.",
        "subtopico": "Cores",
        "topico": "Outros assuntos"
    },
    {
        "id": 78,
        "ingles": "Mahogany",
        "portugues": "Mogno",
        "fraseIngles": "The dining table is mahogany wood.",
        "frasePortugues": "A mesa de jantar é madeira mogno.",
        "subtopico": "Cores",
        "topico": "Outros assuntos"
    },
    {
        "id": 79,
        "ingles": "Walnut brown",
        "portugues": "Marrom nogueira",
        "fraseIngles": "The cabinet is walnut brown.",
        "frasePortugues": "O armário é marrom nogueira.",
        "subtopico": "Cores",
        "topico": "Outros assuntos"
    },
    {
        "id": 80,
        "ingles": "Tan",
        "portugues": "Bronzeado",
        "fraseIngles": "The leather jacket is tan colored.",
        "frasePortugues": "A jaqueta de couro é cor bronzeada.",
        "subtopico": "Cores",
        "topico": "Outros assuntos"
    },
    {
        "id": 81,
        "ingles": "Beige",
        "portugues": "Bege",
        "fraseIngles": "The living room walls are beige.",
        "frasePortugues": "As paredes da sala são bege.",
        "subtopico": "Cores",
        "topico": "Outros assuntos"
    },
    {
        "id": 82,
        "ingles": "Taupe",
        "portugues": "Cinza-amarronzado",
        "fraseIngles": "The carpet is neutral taupe.",
        "frasePortugues": "O tapete é cinza-amarronzado neutro.",
        "subtopico": "Cores",
        "topico": "Outros assuntos"
    },
    {
        "id": 83,
        "ingles": "Sand",
        "portugues": "Areia",
        "fraseIngles": "The beach house is sand colored.",
        "frasePortugues": "A casa de praia é cor de areia.",
        "subtopico": "Cores",
        "topico": "Outros assuntos"
    },
    {
        "id": 84,
        "ingles": "Khaki",
        "portugues": "Cáqui",
        "fraseIngles": "Military pants are khaki colored.",
        "frasePortugues": "Calças militares são cor cáqui.",
        "subtopico": "Cores",
        "topico": "Outros assuntos"
    },
    {
        "id": 85,
        "ingles": "Camel",
        "portugues": "Caramelo",
        "fraseIngles": "The coat is elegant camel color.",
        "frasePortugues": "O casaco é cor caramelo elegante.",
        "subtopico": "Cores",
        "topico": "Outros assuntos"
    },
    {
        "id": 86,
        "ingles": "Jet black",
        "portugues": "Preto azeviche",
        "fraseIngles": "The limousine is jet black.",
        "frasePortugues": "A limusine é preto azeviche.",
        "subtopico": "Cores",
        "topico": "Outros assuntos"
    },
    {
        "id": 87,
        "ingles": "Coal black",
        "portugues": "Preto carvão",
        "fraseIngles": "The night sky is coal black.",
        "frasePortugues": "O céu noturno é preto carvão.",
        "subtopico": "Cores",
        "topico": "Outros assuntos"
    },
    {
        "id": 88,
        "ingles": "Ebony",
        "portugues": "Ébano",
        "fraseIngles": "The piano is polished ebony.",
        "frasePortugues": "O piano é ébano polido.",
        "subtopico": "Cores",
        "topico": "Outros assuntos"
    },
    {
        "id": 89,
        "ingles": "Charcoal",
        "portugues": "Carvão",
        "fraseIngles": "The business suit is charcoal gray.",
        "frasePortugues": "O terno executivo é cinza carvão.",
        "subtopico": "Cores",
        "topico": "Outros assuntos"
    },
    {
        "id": 90,
        "ingles": "Onyx",
        "portugues": "Ônix",
        "fraseIngles": "The stone is deep onyx black.",
        "frasePortugues": "A pedra é preto ônix profundo.",
        "subtopico": "Cores",
        "topico": "Outros assuntos"
    },
    {
        "id": 91,
        "ingles": "Snow white",
        "portugues": "Branco neve",
        "fraseIngles": "The winter landscape is snow white.",
        "frasePortugues": "A paisagem de inverno é branco neve.",
        "subtopico": "Cores",
        "topico": "Outros assuntos"
    },
    {
        "id": 92,
        "ingles": "Pearl white",
        "portugues": "Branco pérola",
        "fraseIngles": "The wedding car is pearl white.",
        "frasePortugues": "O carro de casamento é branco pérola.",
        "subtopico": "Cores",
        "topico": "Outros assuntos"
    },
    {
        "id": 93,
        "ingles": "Cream white",
        "portugues": "Branco creme",
        "fraseIngles": "The kitchen cabinets are cream white.",
        "frasePortugues": "Os armários da cozinha são branco creme.",
        "subtopico": "Cores",
        "topico": "Outros assuntos"
    },
    {
        "id": 94,
        "ingles": "Off-white",
        "portugues": "Branco gelo",
        "fraseIngles": "The walls are painted off-white.",
        "frasePortugues": "As paredes são pintadas de branco gelo.",
        "subtopico": "Cores",
        "topico": "Outros assuntos"
    },
    {
        "id": 95,
        "ingles": "Eggshell white",
        "portugues": "Branco casca de ovo",
        "fraseIngles": "The ceiling is eggshell white.",
        "frasePortugues": "O teto é branco casca de ovo.",
        "subtopico": "Cores",
        "topico": "Outros assuntos"
    },
    {
        "id": 96,
        "ingles": "Silver",
        "portugues": "Prata",
        "fraseIngles": "The car has a silver finish.",
        "frasePortugues": "O carro tem acabamento prata.",
        "subtopico": "Cores",
        "topico": "Outros assuntos"
    },
    {
        "id": 97,
        "ingles": "Platinum",
        "portugues": "Platina",
        "fraseIngles": "The jewelry is platinum colored.",
        "frasePortugues": "A joia é cor de platina.",
        "subtopico": "Cores",
        "topico": "Outros assuntos"
    },
    {
        "id": 98,
        "ingles": "Steel gray",
        "portugues": "Cinza aço",
        "fraseIngles": "The building is steel gray.",
        "frasePortugues": "O prédio é cinza aço.",
        "subtopico": "Cores",
        "topico": "Outros assuntos"
    },
    {
        "id": 99,
        "ingles": "Ash gray",
        "portugues": "Cinza cinza",
        "fraseIngles": "The cat's fur is ash gray.",
        "frasePortugues": "O pelo do gato é cinza cinza.",
        "subtopico": "Cores",
        "topico": "Outros assuntos"
    },
    {
        "id": 100,
        "ingles": "Slate gray",
        "portugues": "Cinza ardósia",
        "fraseIngles": "The roof tiles are slate gray.",
        "frasePortugues": "As telhas do telhado são cinza ardósia.",
        "subtopico": "Cores",
        "topico": "Outros assuntos"
    },
    {
        "id": 101,
        "ingles": "Smoke gray",
        "portugues": "Cinza fumaça",
        "fraseIngles": "The morning mist is smoke gray.",
        "frasePortugues": "A névoa matinal é cinza fumaça.",
        "subtopico": "Cores",
        "topico": "Outros assuntos"
    },
    {
        "id": 102,
        "ingles": "Bright",
        "portugues": "Vivo/brilhante",
        "fraseIngles": "The flowers are bright yellow.",
        "frasePortugues": "As flores são amarelo vivo.",
        "subtopico": "Cores",
        "topico": "Outros assuntos"
    },
    {
        "id": 103,
        "ingles": "Dark",
        "portugues": "Escuro",
        "fraseIngles": "The room has dark blue walls.",
        "frasePortugues": "O quarto tem paredes azul escuro.",
        "subtopico": "Cores",
        "topico": "Outros assuntos"
    },
    {
        "id": 104,
        "ingles": "Light",
        "portugues": "Claro",
        "fraseIngles": "She prefers light green colors.",
        "frasePortugues": "Ela prefere cores verde claro.",
        "subtopico": "Cores",
        "topico": "Outros assuntos"
    },
    {
        "id": 105,
        "ingles": "Pale",
        "portugues": "Pálido",
        "fraseIngles": "The morning sky is pale pink.",
        "frasePortugues": "O céu matinal é rosa pálido.",
        "subtopico": "Cores",
        "topico": "Outros assuntos"
    },
    {
        "id": 106,
        "ingles": "Deep",
        "portugues": "Profundo",
        "fraseIngles": "The ocean is deep blue.",
        "frasePortugues": "O oceano é azul profundo.",
        "subtopico": "Cores",
        "topico": "Outros assuntos"
    },
    {
        "id": 107,
        "ingles": "Rich",
        "portugues": "Rico",
        "fraseIngles": "The velvet curtains are rich purple.",
        "frasePortugues": "As cortinas de veludo são roxo rico.",
        "subtopico": "Cores",
        "topico": "Outros assuntos"
    },
    {
        "id": 108,
        "ingles": "Vivid",
        "portugues": "Vívido",
        "fraseIngles": "The sunset has vivid orange colors.",
        "frasePortugues": "O pôr do sol tem cores laranja vívidas.",
        "subtopico": "Cores",
        "topico": "Outros assuntos"
    },
    {
        "id": 109,
        "ingles": "Muted",
        "portugues": "Apagado",
        "fraseIngles": "The painting uses muted earth tones.",
        "frasePortugues": "A pintura usa tons terrosos apagados.",
        "subtopico": "Cores",
        "topico": "Outros assuntos"
    },
    {
        "id": 110,
        "ingles": "Pastel",
        "portugues": "Pastel",
        "fraseIngles": "The nursery is decorated in pastel colors.",
        "frasePortugues": "O berçário é decorado em cores pastéis.",
        "subtopico": "Cores",
        "topico": "Outros assuntos"
    },
    {
        "id": 111,
        "ingles": "Neon",
        "portugues": "Neon",
        "fraseIngles": "The safety sign is neon orange.",
        "frasePortugues": "A placa de segurança é laranja neon.",
        "subtopico": "Cores",
        "topico": "Outros assuntos"
    },
    {
        "id": 112,
        "ingles": "Fluorescent",
        "portugues": "Fluorescente",
        "fraseIngles": "The highlighter is fluorescent green.",
        "frasePortugues": "O marca-texto é verde fluorescente.",
        "subtopico": "Cores",
        "topico": "Outros assuntos"
    },
    {
        "id": 113,
        "ingles": "Metallic",
        "portugues": "Metálico",
        "fraseIngles": "The car has metallic paint.",
        "frasePortugues": "O carro tem tinta metálica.",
        "subtopico": "Cores",
        "topico": "Outros assuntos"
    },
    {
        "id": 114,
        "ingles": "Matte",
        "portugues": "Fosco",
        "fraseIngles": "The wall paint has a matte finish.",
        "frasePortugues": "A tinta da parede tem acabamento fosco.",
        "subtopico": "Cores",
        "topico": "Outros assuntos"
    },
    {
        "id": 115,
        "ingles": "Glossy",
        "portugues": "Brilhante",
        "fraseIngles": "The table has a glossy surface.",
        "frasePortugues": "A mesa tem superfície brilhante.",
        "subtopico": "Cores",
        "topico": "Outros assuntos"
    },
    {
        "id": 116,
        "ingles": "Shiny",
        "portugues": "Reluzente",
        "fraseIngles": "The new car is shiny red.",
        "frasePortugues": "O carro novo é vermelho reluzente.",
        "subtopico": "Cores",
        "topico": "Outros assuntos"
    },
    {
        "id": 117,
        "ingles": "Dull",
        "portugues": "Opaco",
        "fraseIngles": "The old paint looks dull.",
        "frasePortugues": "A tinta velha parece opaca.",
        "subtopico": "Cores",
        "topico": "Outros assuntos"
    },
    {
        "id": 118,
        "ingles": "Faded",
        "portugues": "Desbotado",
        "fraseIngles": "The old photograph is faded.",
        "frasePortugues": "A fotografia antiga está desbotada.",
        "subtopico": "Cores",
        "topico": "Outros assuntos"
    },
    {
        "id": 119,
        "ingles": "Washed out",
        "portugues": "Desbotado",
        "fraseIngles": "The fabric looks washed out.",
        "frasePortugues": "O tecido parece desbotado.",
        "subtopico": "Cores",
        "topico": "Outros assuntos"
    },
    {
        "id": 120,
        "ingles": "Saturated",
        "portugues": "Saturado",
        "fraseIngles": "The image has saturated colors.",
        "frasePortugues": "A imagem tem cores saturadas.",
        "subtopico": "Cores",
        "topico": "Outros assuntos"
    },
    {
        "id": 121,
        "ingles": "Vibrant",
        "portugues": "Vibrante",
        "fraseIngles": "The tropical birds have vibrant feathers.",
        "frasePortugues": "Os pássaros tropicais têm penas vibrantes.",
        "subtopico": "Cores",
        "topico": "Outros assuntos"
    },
    {
        "id": 122,
        "ingles": "Bold",
        "portugues": "Forte",
        "fraseIngles": "She chose bold red lipstick.",
        "frasePortugues": "Ela escolheu batom vermelho forte.",
        "subtopico": "Cores",
        "topico": "Outros assuntos"
    },
    {
        "id": 123,
        "ingles": "Subtle",
        "portugues": "Sutil",
        "fraseIngles": "The room has subtle color changes.",
        "frasePortugues": "O quarto tem mudanças sutis de cor.",
        "subtopico": "Cores",
        "topico": "Outros assuntos"
    },
    {
        "id": 124,
        "ingles": "Neutral",
        "portugues": "Neutro",
        "fraseIngles": "Beige is a neutral color.",
        "frasePortugues": "Bege é uma cor neutra.",
        "subtopico": "Cores",
        "topico": "Outros assuntos"
    },
    {
        "id": 125,
        "ingles": "Warm",
        "portugues": "Quente",
        "fraseIngles": "Red and orange are warm colors.",
        "frasePortugues": "Vermelho e laranja são cores quentes.",
        "subtopico": "Cores",
        "topico": "Outros assuntos"
    },
    {
        "id": 126,
        "ingles": "Cool",
        "portugues": "Fria",
        "fraseIngles": "Blue and green are cool colors.",
        "frasePortugues": "Azul e verde são cores frias.",
        "subtopico": "Cores",
        "topico": "Outros assuntos"
    },
    {
        "id": 127,
        "ingles": "Primary",
        "portugues": "Primária",
        "fraseIngles": "Red, blue, and yellow are primary colors.",
        "frasePortugues": "Vermelho, azul e amarelo são cores primárias.",
        "subtopico": "Cores",
        "topico": "Outros assuntos"
    },
    {
        "id": 128,
        "ingles": "Secondary",
        "portugues": "Secundária",
        "fraseIngles": "Orange, green, and purple are secondary colors.",
        "frasePortugues": "Laranja, verde e roxo são cores secundárias.",
        "subtopico": "Cores",
        "topico": "Outros assuntos"
    },
    {
        "id": 129,
        "ingles": "Complementary",
        "portugues": "Complementar",
        "fraseIngles": "Red and green are complementary colors.",
        "frasePortugues": "Vermelho e verde são cores complementares.",
        "subtopico": "Cores",
        "topico": "Outros assuntos"
    },
    {
        "id": 130,
        "ingles": "Analogous",
        "portugues": "Análogas",
        "fraseIngles": "Blue and green are analogous colors.",
        "frasePortugues": "Azul e verde são cores análogas.",
        "subtopico": "Cores",
        "topico": "Outros assuntos"
    },
    {
        "id": 131,
        "ingles": "Monochromatic",
        "portugues": "Monocromático",
        "fraseIngles": "The room uses a monochromatic color scheme.",
        "frasePortugues": "O quarto usa esquema de cores monocromático.",
        "subtopico": "Cores",
        "topico": "Outros assuntos"
    },
    {
        "id": 132,
        "ingles": "Rainbow",
        "portugues": "Arco-íris",
        "fraseIngles": "The rainbow shows all colors.",
        "frasePortugues": "O arco-íris mostra todas as cores.",
        "subtopico": "Cores",
        "topico": "Outros assuntos"
    },
    {
        "id": 133,
        "ingles": "Spectrum",
        "portugues": "Espectro",
        "fraseIngles": "Light creates a color spectrum.",
        "frasePortugues": "Luz cria um espectro de cores.",
        "subtopico": "Cores",
        "topico": "Outros assuntos"
    },
    {
        "id": 134,
        "ingles": "Hue",
        "portugues": "Matiz",
        "fraseIngles": "The hue changes from red to orange.",
        "frasePortugues": "O matiz muda de vermelho para laranja.",
        "subtopico": "Cores",
        "topico": "Outros assuntos"
    },
    {
        "id": 135,
        "ingles": "Shade",
        "portugues": "Tom",
        "fraseIngles": "This shade of blue is darker.",
        "frasePortugues": "Este tom de azul é mais escuro.",
        "subtopico": "Cores",
        "topico": "Outros assuntos"
    },
    {
        "id": 136,
        "ingles": "Tint",
        "portugues": "Nuance",
        "fraseIngles": "Add white to create a lighter tint.",
        "frasePortugues": "Adicione branco para criar uma nuance mais clara.",
        "subtopico": "Cores",
        "topico": "Outros assuntos"
    },
    {
        "id": 137,
        "ingles": "Tone",
        "portugues": "Tonalidade",
        "fraseIngles": "The painting has a warm tone.",
        "frasePortugues": "A pintura tem uma tonalidade quente.",
        "subtopico": "Cores",
        "topico": "Outros assuntos"
    },
    {
        "id": 138,
        "ingles": "Pigment",
        "portugues": "Pigmento",
        "fraseIngles": "Artists mix pigments to create colors.",
        "frasePortugues": "Artistas misturam pigmentos para criar cores.",
        "subtopico": "Cores",
        "topico": "Outros assuntos"
    },
    {
        "id": 139,
        "ingles": "Dye",
        "portugues": "Tintura",
        "fraseIngles": "The fabric is colored with natural dye.",
        "frasePortugues": "O tecido é colorido com tintura natural.",
        "subtopico": "Cores",
        "topico": "Outros assuntos"
    },
    {
        "id": 140,
        "ingles": "Paint",
        "portugues": "Tinta",
        "fraseIngles": "Mix different paints to get new colors.",
        "frasePortugues": "Misture tintas diferentes para obter cores novas.",
        "subtopico": "Cores",
        "topico": "Outros assuntos"
    },
    {
        "id": 141,
        "ingles": "Ink",
        "portugues": "Tinta (líquida)",
        "fraseIngles": "The printer ran out of blue ink.",
        "frasePortugues": "A impressora ficou sem tinta azul.",
        "subtopico": "Cores",
        "topico": "Outros assuntos"
    },
    {
        "id": 142,
        "ingles": "Colored",
        "portugues": "Colorido",
        "fraseIngles": "The children drew with colored pencils.",
        "frasePortugues": "As crianças desenharam com lápis coloridos.",
        "subtopico": "Cores",
        "topico": "Outros assuntos"
    },
    {
        "id": 143,
        "ingles": "Colorful",
        "portugues": "Colorido/vistoso",
        "fraseIngles": "The garden is colorful in spring.",
        "frasePortugues": "O jardim é colorido na primavera.",
        "subtopico": "Cores",
        "topico": "Outros assuntos"
    },
    {
        "id": 144,
        "ingles": "Colorless",
        "portugues": "Incolor",
        "fraseIngles": "Water is colorless and transparent.",
        "frasePortugues": "Água é incolor e transparente.",
        "subtopico": "Cores",
        "topico": "Outros assuntos"
    },
    {
        "id": 145,
        "ingles": "Multicolored",
        "portugues": "Multicolorido",
        "fraseIngles": "The quilt is beautiful and multicolored.",
        "frasePortugues": "A colcha é linda e multicolorida.",
        "subtopico": "Cores",
        "topico": "Outros assuntos"
    },
    {
        "id": 146,
        "ingles": "Two-toned",
        "portugues": "Bicolor",
        "fraseIngles": "The car has a two-toned paint job.",
        "frasePortugues": "O carro tem pintura bicolor.",
        "subtopico": "Cores",
        "topico": "Outros assuntos"
    },
    {
        "id": 147,
        "ingles": "Striped",
        "portugues": "Listrado",
        "fraseIngles": "The shirt has blue and white stripes.",
        "frasePortugues": "A camisa tem listras azuis e brancas.",
        "subtopico": "Cores",
        "topico": "Outros assuntos"
    },
    {
        "id": 148,
        "ingles": "Spotted",
        "portugues": "Pintalgado",
        "fraseIngles": "The dog has a spotted coat.",
        "frasePortugues": "O cão tem pelagem pintalgada.",
        "subtopico": "Cores",
        "topico": "Outros assuntos"
    },
    {
        "id": 149,
        "ingles": "Solid",
        "portugues": "Liso/sólido",
        "fraseIngles": "She prefers solid colors over patterns.",
        "frasePortugues": "Ela prefere cores lisas a estampas.",
        "subtopico": "Cores",
        "topico": "Outros assuntos"
    },
    {
        "id": 150,
        "ingles": "Mixed",
        "portugues": "Misturado",
        "fraseIngles": "The artist used mixed colors.",
        "frasePortugues": "O artista usou cores misturadas.",
        "subtopico": "Cores",
        "topico": "Outros assuntos"
    },
    {
        "id": 151,
        "ingles": "Blended",
        "portugues": "Misturado suavemente",
        "fraseIngles": "The sunset colors are beautifully blended.",
        "frasePortugues": "As cores do pôr do sol estão lindamente misturadas.",
        "subtopico": "Cores",
        "topico": "Outros assuntos"
    },
    {
        "id": 152,
        "ingles": "Contrasting",
        "portugues": "Contrastante",
        "fraseIngles": "Black and white are contrasting colors.",
        "frasePortugues": "Preto e branco são cores contrastantes.",
        "subtopico": "Cores",
        "topico": "Outros assuntos"
    },
    {
        "id": 153,
        "ingles": "Matching",
        "portugues": "Combinando",
        "fraseIngles": "Her shoes and bag are matching colors.",
        "frasePortugues": "Seus sapatos e bolsa são cores combinando.",
        "subtopico": "Cores",
        "topico": "Outros assuntos"
    },
    {
        "id": 154,
        "ingles": "Clashing",
        "portugues": "Conflitante",
        "fraseIngles": "Those colors are clashing together.",
        "frasePortugues": "Essas cores estão conflitantes juntas.",
        "subtopico": "Cores",
        "topico": "Outros assuntos"
    },
    {
        "id": 155,
        "ingles": "Harmonious",
        "portugues": "Harmoniosas",
        "fraseIngles": "The room's colors are harmonious.",
        "frasePortugues": "As cores do quarto são harmoniosas.",
        "subtopico": "Cores",
        "topico": "Outros assuntos"
    },
    {
        "id": 156,
        "ingles": "Balanced",
        "portugues": "Equilibradas",
        "fraseIngles": "The painting has balanced colors.",
        "frasePortugues": "A pintura tem cores equilibradas.",
        "subtopico": "Cores",
        "topico": "Outros assuntos"
    }
]