{
  "titulo": "Horas em Inglês",
  "descricao": "Aprenda a falar e perguntar as horas em inglês! Domine os dois sistemas (12h e 24h) e expressões de tempo essenciais.",
  "secoes": [
    {
      "id": "introducao",
      "titulo": "Telling Time in English",
      "tipo": "texto",
      "conteudo": {
        "texto_ingles": "Learning to tell time in English is essential for daily communication! English uses both 12-hour and 24-hour formats, but the 12-hour system with AM/PM is more common in everyday conversation. We'll learn different ways to express time, from basic hours to specific minutes, plus useful time expressions.",
        "texto_portugues": "Aprender a falar as horas em inglês é essencial para comunicação diária! O inglês usa tanto o formato de 12 horas quanto o de 24 horas, mas o sistema de 12 horas com AM/PM é mais comum em conversas do dia a dia. Vamos aprender diferentes maneiras de expressar tempo, desde horas básicas até minutos específicos, além de expressões úteis de tempo.",
        "tem_audio": true
      }
    },
    {
      "id": "perguntando_horas",
      "titulo": "Asking for Time",
      "tipo": "vocabulario",
      "descricao": "Como perguntar as horas em inglês",
      "itens": [
        {
          "ingles": "What time is it?",
          "portugues": "Que horas são?",
          "fonetica": "/wʌt taɪm ɪz ɪt/",
          "tem_audio": true,
          "contexto": "Most common way to ask for time"
        },
        {
          "ingles": "Do you have the time?",
          "portugues": "Você tem as horas?",
          "fonetica": "/du ju hæv ðə taɪm/",
          "tem_audio": true,
          "contexto": "Polite way to ask for time"
        },
        {
          "ingles": "Could you tell me the time, please?",
          "portugues": "Poderia me dizer as horas, por favor?",
          "fonetica": "/kʊd ju tɛl mi ðə taɪm pliz/",
          "tem_audio": true,
          "contexto": "Very polite and formal way"
        },
        {
          "ingles": "What's the time?",
          "portugues": "Qual é a hora?",
          "fonetica": "/wʌts ðə taɪm/",
          "tem_audio": true,
          "contexto": "Informal way to ask for time"
        }
      ]
    },
    {
      "id": "horas_exatas",
      "titulo": "Exact Hours - O'clock",
      "tipo": "vocabulario",
      "descricao": "Horas exatas usando o'clock",
      "itens": [
        {
          "ingles": "It's one o'clock.",
          "portugues": "É uma hora.",
          "fonetica": "/ɪts wʌn əˈklɑk/",
          "tem_audio": true,
          "contexto": "1:00 - use 'one' not 'a' for time"
        },
        {
          "ingles": "It's three o'clock.",
          "portugues": "São três horas.",
          "fonetica": "/ɪts θri əˈklɑk/",
          "tem_audio": true,
          "contexto": "3:00 - O'CLOCK only for exact hours"
        },
        {
          "ingles": "It's twelve o'clock.",
          "portugues": "São doze horas.",
          "fonetica": "/ɪts twɛlv əˈklɑk/",
          "tem_audio": true,
          "contexto": "12:00 - can be noon or midnight"
        },
        {
          "ingles": "It's seven o'clock in the morning.",
          "portugues": "São sete horas da manhã.",
          "fonetica": "/ɪts ˈsɛvən əˈklɑk ɪn ðə ˈmɔrnɪŋ/",
          "tem_audio": true,
          "contexto": "7:00 AM - adding time of day for clarity"
        },
        {
          "ingles": "It's nine o'clock at night.",
          "portugues": "São nove horas da noite.",
          "fonetica": "/ɪts naɪn əˈklɑk æt naɪt/",
          "tem_audio": true,
          "contexto": "9:00 PM - evening time specification"
        }
      ]
    },
    {
      "id": "am_pm",
      "titulo": "AM and PM System",
      "tipo": "vocabulario",
      "descricao": "Sistema AM (manhã) e PM (tarde/noite)",
      "itens": [
        {
          "ingles": "It's 8 AM. (eight AM)",
          "portugues": "São 8h da manhã.",
          "fonetica": "/ɪts eɪt ˌeɪˈɛm/",
          "tem_audio": true,
          "contexto": "AM = morning hours (midnight to noon)"
        },
        {
          "ingles": "It's 2 PM. (two PM)",
          "portugues": "São 2h da tarde.",
          "fonetica": "/ɪts tu ˌpiˈɛm/",
          "tem_audio": true,
          "contexto": "PM = afternoon/evening hours (noon to midnight)"
        },
        {
          "ingles": "The meeting is at 10:30 AM.",
          "portugues": "A reunião é às 10:30 da manhã.",
          "fonetica": "/ðə ˈmitɪŋ ɪz æt ˈtɛn ˈθɜrti ˌeɪˈɛm/",
          "tem_audio": true,
          "contexto": "10:30 AM - specific time with minutes"
        },
        {
          "ingles": "I go to bed at 11 PM.",
          "portugues": "Eu vou dormir às 11h da noite.",
          "fonetica": "/aɪ goʊ tu bɛd æt ɪˈlɛvən ˌpiˈɛm/",
          "tem_audio": true,
          "contexto": "11 PM - evening routine time"
        },
        {
          "ingles": "It's 12 PM. (noon)",
          "portugues": "São 12h. (meio-dia)",
          "fonetica": "/ɪts twɛlv ˌpiˈɛm/",
          "tem_audio": true,
          "contexto": "12 PM = noon, 12 AM = midnight"
        }
      ]
    },
    {
      "id": "minutos_quarter_half",
      "titulo": "Quarter and Half Hours",
      "tipo": "vocabulario",
      "descricao": "Expressões especiais para 15, 30 e 45 minutos",
      "itens": [
        {
          "ingles": "It's quarter past two. (2:15)",
          "portugues": "São duas e quinze. (2:15)",
          "fonetica": "/ɪts ˈkwɔrtər pæst tu/",
          "tem_audio": true,
          "contexto": "QUARTER PAST = 15 minutes after the hour"
        },
        {
          "ingles": "It's half past three. (3:30)",
          "portugues": "São três e meia. (3:30)",
          "fonetica": "/ɪts hæf pæst θri/",
          "tem_audio": true,
          "contexto": "HALF PAST = 30 minutes after the hour"
        },
        {
          "ingles": "It's quarter to four. (3:45)",
          "portugues": "São quinze para as quatro. (3:45)",
          "fonetica": "/ɪts ˈkwɔrtər tu fɔr/",
          "tem_audio": true,
          "contexto": "QUARTER TO = 15 minutes before the next hour"
        },
        {
          "ingles": "It's twenty past five. (5:20)",
          "portugues": "São cinco e vinte. (5:20)",
          "fonetica": "/ɪts ˈtwɛnti pæst faɪv/",
          "tem_audio": true,
          "contexto": "PAST = minutes after the hour (1-30 minutes)"
        },
        {
          "ingles": "It's ten to six. (5:50)",
          "portugues": "São dez para as seis. (5:50)",
          "fonetica": "/ɪts tɛn tu sɪks/",
          "tem_audio": true,
          "contexto": "TO = minutes before the next hour (31-59 minutes)"
        }
      ]
    },
    {
      "id": "minutos_especificos",
      "titulo": "Specific Minutes - Two Ways",
      "tipo": "vocabulario",
      "descricao": "Duas formas de dizer minutos específicos",
      "itens": [
        {
          "ingles": "It's two fifteen. / It's quarter past two.",
          "portugues": "São duas e quinze. / São duas e quinze.",
          "fonetica": "/ɪts tu ˈfɪfˈtin / ɪts ˈkwɔrtər pæst tu/",
          "tem_audio": true,
          "contexto": "2:15 - American style vs British style"
        },
        {
          "ingles": "It's four thirty. / It's half past four.",
          "portugues": "São quatro e trinta. / São quatro e meia.",
          "fonetica": "/ɪts fɔr ˈθɜrti / ɪts hæf pæst fɔr/",
          "tem_audio": true,
          "contexto": "4:30 - direct time vs traditional expression"
        },
        {
          "ingles": "It's six forty-five. / It's quarter to seven.",
          "portugues": "São seis e quarenta e cinco. / São quinze para as sete.",
          "fonetica": "/ɪts sɪks ˈfɔrti faɪv / ɪts ˈkwɔrtər tu ˈsɛvən/",
          "tem_audio": true,
          "contexto": "6:45 - two different but correct ways"
        },
        {
          "ingles": "It's eight oh five. (8:05)",
          "portugues": "São oito e cinco. (8:05)",
          "fonetica": "/ɪts eɪt oʊ faɪv/",
          "tem_audio": true,
          "contexto": "OH for zero when saying single digit minutes"
        }
      ]
    },
    {
      "id": "expressoes_especiais",
      "titulo": "Special Time Expressions",
      "tipo": "vocabulario",
      "descricao": "Expressões especiais de tempo",
      "itens": [
        {
          "ingles": "It's noon. / It's midnight.",
          "portugues": "É meio-dia. / É meia-noite.",
          "fonetica": "/ɪts nun / ɪts ˈmɪdˌnaɪt/",
          "tem_audio": true,
          "contexto": "NOON = 12 PM, MIDNIGHT = 12 AM"
        },
        {
          "ingles": "It's almost three o'clock.",
          "portugues": "São quase três horas.",
          "fonetica": "/ɪts ˈɔlˌmoʊst θri əˈklɑk/",
          "tem_audio": true,
          "contexto": "ALMOST = nearly, close to the time"
        },
        {
          "ingles": "It's exactly five thirty.",
          "portugues": "São exatamente cinco e meia.",
          "fonetica": "/ɪts ɪgˈzæktli faɪv ˈθɜrti/",
          "tem_audio": true,
          "contexto": "EXACTLY = precisely that time"
        },
        {
          "ingles": "It's about four o'clock.",
          "portugues": "São mais ou menos quatro horas.",
          "fonetica": "/ɪts əˈbaʊt fɔr əˈklɑk/",
          "tem_audio": true,
          "contexto": "ABOUT = approximately, around that time"
        },
        {
          "ingles": "It's just after six.",
          "portugues": "Passou um pouquinho das seis.",
          "fonetica": "/ɪts dʒʌst ˈæftər sɪks/",
          "tem_audio": true,
          "contexto": "JUST AFTER = a few minutes past the hour"
        }
      ]
    },
    {
      "id": "sistema_24_horas",
      "titulo": "24-Hour System (Military Time)",
      "tipo": "vocabulario",
      "descricao": "Sistema de 24 horas (usado em horários oficiais)",
      "itens": [
        {
          "ingles": "The train leaves at 14:30. (fourteen thirty)",
          "portugues": "O trem parte às 14:30. (quatorze e trinta)",
          "fonetica": "/ðə treɪn livz æt ˈfɔrˌtin ˈθɜrti/",
          "tem_audio": true,
          "contexto": "24-hour format: 14:30 = 2:30 PM"
        },
        {
          "ingles": "The store opens at 09:00. (oh nine hundred)",
          "portugues": "A loja abre às 09:00. (nove horas)",
          "fonetica": "/ðə stɔr ˈoʊpənz æt oʊ naɪn ˈhʌndrəd/",
          "tem_audio": true,
          "contexto": "09:00 in 24-hour = 9:00 AM"
        },
        {
          "ingles": "The flight departs at 23:45. (twenty-three forty-five)",
          "portugues": "O voo parte às 23:45. (vinte e três e quarenta e cinco)",
          "fonetica": "/ðə flaɪt dɪˈpɑrts æt ˈtwɛnti θri ˈfɔrti faɪv/",
          "tem_audio": true,
          "contexto": "23:45 = 11:45 PM in 12-hour format"
        }
      ]
    },
    {
      "id": "preposicoes_tempo",
      "titulo": "Prepositions with Time",
      "tipo": "vocabulario",
      "descricao": "Preposições usadas com expressões de tempo",
      "itens": [
        {
          "ingles": "The meeting is at 3 o'clock.",
          "portugues": "A reunião é às 3 horas.",
          "fonetica": "/ðə ˈmitɪŋ ɪz æt θri əˈklɑk/",
          "tem_audio": true,
          "contexto": "AT - used with specific times"
        },
        {
          "ingles": "I work from 9 to 5.",
          "portugues": "Eu trabalho das 9 às 5.",
          "fonetica": "/aɪ wɜrk frʌm naɪn tu faɪv/",
          "tem_audio": true,
          "contexto": "FROM...TO - showing time duration"
        },
        {
          "ingles": "The store is open until 10 PM.",
          "portugues": "A loja fica aberta até as 10h da noite.",
          "fonetica": "/ðə stɔr ɪz ˈoʊpən ənˈtɪl tɛn ˌpiˈɛm/",
          "tem_audio": true,
          "contexto": "UNTIL - up to that time"
        },
        {
          "ingles": "I'll be there by 6 o'clock.",
          "portugues": "Estarei lá até as 6 horas.",
          "fonetica": "/aɪl bi ðɛr baɪ sɪks əˈklɑk/",
          "tem_audio": true,
          "contexto": "BY - not later than that time"
        },
        {
          "ingles": "The class starts in 15 minutes.",
          "portugues": "A aula começa em 15 minutos.",
          "fonetica": "/ðə klæs stɑrts ɪn ˈfɪfˈtin ˈmɪnəts/",
          "tem_audio": true,
          "contexto": "IN - after that amount of time"
        }
      ]
    },
    {
      "id": "horarios_rotina",
      "titulo": "Daily Routine Times",
      "tipo": "vocabulario",
      "descricao": "Horários comuns da rotina diária",
      "itens": [
        {
          "ingles": "I wake up at 6:30 AM.",
          "portugues": "Eu acordo às 6:30 da manhã.",
          "fonetica": "/aɪ weɪk ʌp æt sɪks ˈθɜrti ˌeɪˈɛm/",
          "tem_audio": true,
          "contexto": "Morning routine - wake up time"
        },
        {
          "ingles": "Breakfast is at 7:15 AM.",
          "portugues": "O café da manhã é às 7:15 da manhã.",
          "fonetica": "/ˈbrɛkfəst ɪz æt ˈsɛvən ˈfɪfˈtin ˌeɪˈɛm/",
          "tem_audio": true,
          "contexto": "Meal time schedule"
        },
        {
          "ingles": "I leave for work at 8 o'clock sharp.",
          "portugues": "Eu saio para o trabalho às 8 horas em ponto.",
          "fonetica": "/aɪ liv fɔr wɜrk æt eɪt əˈklɑk ʃɑrp/",
          "tem_audio": true,
          "contexto": "SHARP = exactly at that time"
        },
        {
          "ingles": "Lunch break is from 12 to 1 PM.",
          "portugues": "O intervalo do almoço é das 12h à 1h da tarde.",
          "fonetica": "/lʌntʃ breɪk ɪz frʌm twɛlv tu wʌn ˌpiˈɛm/",
          "tem_audio": true,
          "contexto": "Work schedule - break time"
        },
        {
          "ingles": "I get home around 6:30 PM.",
          "portugues": "Eu chego em casa por volta das 6:30 da tarde.",
          "fonetica": "/aɪ gɛt hoʊm əˈraʊnd sɪks ˈθɜrti ˌpiˈɛm/",
          "tem_audio": true,
          "contexto": "AROUND = approximately, about that time"
        }
      ]
    },
    {
      "id": "dialogo_exemplo",
      "titulo": "Real Life Dialogue - Making Appointments",
      "tipo": "dialogo",
      "descricao": "Conversa real marcando horários",
      "participantes": ["Receptionist", "Patient"],
      "conversas": [
        {
          "falante": "Receptionist",
          "ingles": "Good morning! How can I help you today?",
          "portugues": "Bom dia! Como posso ajudá-lo hoje?",
          "fonetica": "/gʊd ˈmɔrnɪŋ haʊ kæn aɪ hɛlp ju təˈdeɪ/",
          "tem_audio": true
        },
        {
          "falante": "Patient",
          "ingles": "Hi! I'd like to schedule an appointment with Dr. Smith. What time is available this week?",
          "portugues": "Oi! Eu gostaria de marcar uma consulta com o Dr. Smith. Que horário está disponível esta semana?",
          "fonetica": "/haɪ aɪd laɪk tu ˈskɛdʒul æn əˈpɔɪntmənt wɪð ˈdɑktər smɪθ wʌt taɪm ɪz əˈveɪləbəl ðɪs wik/",
          "tem_audio": true
        },
        {
          "falante": "Receptionist",
          "ingles": "Let me check... We have an opening tomorrow at 2:30 PM or Thursday at quarter past ten in the morning.",
          "portugues": "Deixe-me verificar... Temos uma vaga amanhã às 2:30 da tarde ou quinta-feira às dez e quinze da manhã.",
          "fonetica": "/lɛt mi tʃɛk wi hæv æn ˈoʊpənɪŋ təˈmɑroʊ æt tu ˈθɜrti ˌpiˈɛm ɔr ˈθɜrzˌdeɪ æt ˈkwɔrtər pæst tɛn ɪn ðə ˈmɔrnɪŋ/",
          "tem_audio": true
        },
        {
          "falante": "Patient",
          "ingles": "Thursday morning works better for me. So that's 10:15 AM, right?",
          "portugues": "Quinta de manhã funciona melhor para mim. Então são 10:15 da manhã, certo?",
          "fonetica": "/ˈθɜrzˌdeɪ ˈmɔrnɪŋ wɜrks ˈbɛtər fɔr mi soʊ ðæts tɛn ˈfɪfˈtin ˌeɪˈɛm raɪt/",
          "tem_audio": true
        },
        {
          "falante": "Receptionist",
          "ingles": "Exactly! Please arrive about 15 minutes early to fill out forms. The appointment should last until 11:00 AM.",
          "portugues": "Exatamente! Por favor chegue cerca de 15 minutos mais cedo para preencher formulários. A consulta deve durar até as 11:00 da manhã.",
          "fonetica": "/ɪgˈzæktli pliz əˈraɪv əˈbaʊt ˈfɪfˈtin ˈmɪnəts ˈɜrli tu fɪl aʊt fɔrmz ði əˈpɔɪntmənt ʃʊd læst ənˈtɪl ɪˈlɛvən ˌeɪˈɛm/",
          "tem_audio": true
        },
        {
          "falante": "Patient",
          "ingles": "Perfect! So I should be there by 10 o'clock. What time do you close on Thursdays?",
          "portugues": "Perfeito! Então eu devo estar lá às 10 horas. A que horas vocês fecham nas quintas?",
          "fonetica": "/ˈpɜrfɪkt soʊ aɪ ʃʊd bi ðɛr baɪ tɛn əˈklɑk wʌt taɪm du ju kloʊz ɑn ˈθɜrzˌdeɪz/",
          "tem_audio": true
        }
      ]
    },
    {
      "id": "texto_pratica",
      "titulo": "Practice Text - Daily Schedule",
      "tipo": "texto",
      "conteudo": {
        "texto_ingles": "My typical weekday starts early. I wake up at exactly 6:00 AM and immediately check the time on my phone. By quarter past six, I'm already in the shower. Breakfast is always at 7:00 AM sharp - I never skip it! I leave home at 7:45 AM because my commute takes about 45 minutes. The train departs at 8:02 AM, and I arrive downtown at 8:47 AM. My office hours are from 9:00 AM to 5:30 PM, with a lunch break from noon to 1:00 PM. I usually eat lunch at half past twelve. In the afternoon, I have a team meeting every Tuesday at quarter to three. I finish work at exactly 5:30 PM and catch the 5:45 PM train home. I get home around 6:30 PM, just in time for dinner. We eat dinner at 7:00 PM as a family. I go to bed at 10:30 PM, but I'm usually asleep by 11:00 PM. On weekends, everything changes - I sleep until 8:00 AM and have a relaxed breakfast at 9:00 AM. Time really flies when you have a good routine!",
        "texto_portugues": "Meu dia de semana típico começa cedo. Eu acordo exatamente às 6:00 da manhã e imediatamente verifico as horas no meu celular. Às seis e quinze, já estou no chuveiro. O café da manhã é sempre às 7:00 em ponto - nunca pulo! Saio de casa às 7:45 porque meu trajeto leva cerca de 45 minutos. O trem parte às 8:02 da manhã, e chego no centro às 8:47. Meu horário de trabalho é das 9:00 às 17:30, com intervalo de almoço do meio-dia à 1:00 da tarde. Geralmente almoço às doze e meia. À tarde, tenho uma reunião de equipe toda terça às quinze para as três. Termino o trabalho exatamente às 17:30 e pego o trem das 17:45 para casa. Chego em casa por volta das 18:30, bem na hora do jantar. Jantamos às 19:00 em família. Vou dormir às 22:30, mas geralmente estou dormindo às 23:00. Nos fins de semana, tudo muda - durmo até as 8:00 e tomo um café da manhã relaxante às 9:00. O tempo realmente voa quando você tem uma boa rotina!",
        "tem_audio": true
      }
    },
    {
      "id": "dicas_importantes",
      "titulo": "Essential Tips for Telling Time",
      "tipo": "texto",
      "conteudo": {
        "texto_ingles": "Remember these key points: 1) Use 'AT' with specific times (at 3 o'clock, at 2:30). 2) For 1-30 minutes, use 'PAST' (twenty past five). For 31-59 minutes, use 'TO' (twenty to six). 3) 'O'clock' is only for exact hours (3 o'clock, not 3:15 o'clock). 4) AM/PM or specify morning/afternoon to avoid confusion. 5) 'Sharp' means exactly on time. 6) In digital format, say 'oh' for single zeros (8:05 = eight oh five).",
        "texto_portugues": "Lembre-se desses pontos-chave: 1) Use 'AT' com horários específicos (at 3 o'clock, at 2:30). 2) Para 1-30 minutos, use 'PAST' (twenty past five). Para 31-59 minutos, use 'TO' (twenty to six). 3) 'O'clock' é apenas para horas exatas (3 o'clock, não 3:15 o'clock). 4) AM/PM ou especifique manhã/tarde para evitar confusão. 5) 'Sharp' significa exatamente na hora. 6) No formato digital, diga 'oh' para zeros únicos (8:05 = eight oh five).",
        "tem_audio": true
      }
    },
    {
      "id": "pratica_final",
      "titulo": "Your Turn to Practice!",
      "tipo": "texto",
      "conteudo": {
        "texto_ingles": "Now practice! Look at clocks around you and say the time out loud in English. Practice both ways: digital (two thirty) and traditional (half past two). Create sentences about your daily schedule using different time expressions. Ask family or friends 'What time is it?' and practice answering. Try scheduling appointments using specific times. Remember: telling time accurately is essential for punctuality and daily communication!",
        "texto_portugues": "Agora pratique! Olhe relógios ao seu redor e diga as horas em voz alta em inglês. Pratique das duas formas: digital (two thirty) e tradicional (half past two). Crie frases sobre sua agenda diária usando diferentes expressões de tempo. Pergunte a familiares ou amigos 'What time is it?' e pratique respondendo. Tente marcar compromissos usando horários específicos. Lembre-se: dizer as horas com precisão é essencial para pontualidade e comunicação diária!",
        "tem_audio": true
      }
    }
  ]
}
